Workbook

Sheet Dashboard & Projections
A1: ALTURA HOUSEHOLD CONVERGENCE FEASIBILITY DASHBOARD
A3: KEY STRATEGIC METRICS (COHORT OF 1,000 SWITCHERS)
A4: Metric Description | B4: Single-play (Standalone) | C4: Triple-play (Family Secure Bundle) | D4: Improvement Multiplier | E4: Financial & Strategic Justification
A5: Annual Customer Churn Rate | B5: 0.22 | C5: 0.05 | D5: =(B5-C5)/B5 | E5: 77.3% Churn reduction dramatically extends customer lifetime.
A6: Average Customer Lifetime (Years) | B6: =1/(B5) | C6: =1/(C5) | D6: =C6/B6 | E6: Customer relationship extends from 4.5 to 20 years.
A7: Average Monthly Customer ARPU | B7: 1299 | C7: 1449 | D7: =C7/B7 | E7: Captures 1.12x direct wallet share while consolidating utilities.
A8: Net EBITDA Customer Lifetime Value (LTV) | B8: 20226 | C8: 97511 | D8: =C8/B8 | E8: 4.82x EBITDA contribution increase per household.
A9: Ecosystem Return on Investment (ROI) | B9: 22.744444 | C9: 33.41 | D9: =C9/B9 | E9: Yields 33.4x return on initial hardware subsidy + CAC outlay.
A11: COHORT FINANCIAL FEASIBILITY SUMMARY
A12: Feasibility Metric Group | B12: Value Detail | C12: Slide Reference Takeaway
A13: Development Costs Amortization | B13: ₹20,00,000 (One-time) | C13: Amortized to ₹2,000 per switcher for initial 1,000 subscriber goal
A14: Ecosystem Initial Capex (Hardware) | B14: ₹48,00,000 (₹4,800/HH) | C14: Fully provisioned router + STB box + camera. Waived to eliminate migration dread
A15: Outbound MNP Acquisition CAC | B15: ₹15,30,000 (₹1,530/HH) | C15: Includes ₹500 MNP switcher rebate + labor + commission + marketing
A16: Weighted EBITDA Margin | B16: 0.2747 | C16: EBITDA margin of 27.5% yields ₹412/mo (promo) & ₹914/mo (standard) per user
A17: Customer Payback Period | B17: 8.6 Months | C17: All initial hardware Capex + switcher CAC fully recovered in under 9 months
A18: Net Cohort EBITDA (24-Month) | B18: ₹1.15 Crores (₹1,15,44,000) | C18: Total cumulative cash flow profit after fully amortizing dev cost

Sheet Slide Contents
A1: POWERPOINT PRESENTATION SLIDE CONTENTS
A3: Slide Reference | B3: Content Heading | C3: Sub-headline / Context | D3: Bullet Point Content | E3: Key Strategic Takeaway
A4: Slide 2: Solution | B4: Altura Home: A Frictionless, Dual-Engine Ecosystem for Household Convergence | C4: Targeting urban high-value households through inbound digital conversion and outbound competitor poaching. | D4: 1. Inbound Product & Digital Core: - 4 Value-driven tiers (Starter, Connect, Family Secure, Infinite) bundling fiber, mobile, satellite TV, bank, cloud, and security. - Interactive Build-Your-Own-Bundle customizer showing real-time savings to dismantle Utility-Arbitrage Bias. - AirBot AI digital concierge to simplify profile matching and eliminate onboarding friction. 2. Outbound Reachout/Poaching Engine: - Doorstep MNP in 15 Minutes: Eqquiping in-home fiber/broadband installation technicians with mobile activation apps to execute instant SIM swaps on-site. - Switcher's Contract Rebate: One-time ₹500 cashback credit on the first bill to buyout competitor contract penalty fees. - Security Network Failover: Positioning Altura Xsafe smart cameras with automatic low-power cellular network failover backup to solve Single Point of Failure (SPOF) anxiety. | E4: Competitor users (Jio/Vi) are won over by removing structural setup dread and financial switching friction at their doorsteps.
A5: Slide 3: Feasibility | B5: Financial Feasibility: Churn-Driven LTV Multipliers & High-Return Cohort Economics | C5: Amortizing upfront development, hardware subsidy, and switcher rebates through high-retention monthly recurring EBITDA margins. | D5: 1. Acquisition & Provisioning Capex/CAC: - Website/Portal Development: ₹20 Lakhs amortized (₹2,000/customer). - Hardware Provisioning: ₹4,800/HH (subsidized dual-band Wi-Fi router, DTH smart box, Xsafe camera) to waiving migration cost. - Outbound MNP CAC: ₹1,530/customer (₹500 switcher rebate, labor, runner delivery, tech commission, local marketing). 2. Detailed Operating & Return Economics: - Recurring monthly Opex: ₹535/mo per user (bandwidth, content licensing, cellular tower pool, Google bulk royalty, cloud storage, bank administration). - Payback Period: The initial ₹6,330 hardware Capex + switcher CAC is fully recovered in 8.6 Months (inclusive of 3-mos promo ₹999/mo). - Weighted EBITDA Margin: 27.5% on standard ₹1,499/mo plan (yielding ₹914/mo EBITDA profit). - Churn Arbitrage LTV: Reducing churn from 22.0% (standalone) to 5.0% (triple-play) extends lifetime to 20 years, yielding ₹97,511 Net EBITDA LTV (4.82x multiplier) and 33.4x ROI. | E5: waiving upfront hardware and contract buyout costs is mathematically sound, yielding ₹1.15 Cr cohort profit in 24 months.

Sheet Detailed Cost Breakdown
A1: ALTURA HOUSEHOLD CONVERGENCE COMPREHENSIVE COST CATALOG
A3: 1. ONE-TIME CAPITAL & DEVELOPMENT COSTS (CAPEX)
A4: Cost Item | B4: Bulk Procurement Price (₹) | C4: Customer Charging (₹) | D4: Net Altura Subsidy (₹) | E4: Amortization Rule | F4: Strategic Business Justification
A5: Website & AI Portal Development | B5: 2000000 | C5: 0 | D5: 2000000 | E5: Amortized over first 1,000 cohort (₹2,000/HH) | F5: Design, customizer custom frontend, AirBot AI NLP training, APIs
A6: Dual-Band ONT Wi-Fi Router | B6: 1500 | C6: 0 | D6: 1500 | E6: Amortized over customer contract lifetime | F6: Waived to eliminate migration barrier; high-speed home connectivity anchor
A7: Altura Xstream 4K Smart Android Box | B7: 1800 | C7: 0 | D7: 1800 | E7: Amortized over customer contract lifetime | F7: Waived; hybrid satellite/OTT television anchor to stop DTH revenue drop
A8: Altura Xsafe AI Smart Security Camera | B8: 1500 | C8: 0 | D8: 1500 | E8: Amortized over customer contract lifetime | F8: Waived; smart home security camera enlisting cell-failover backup tech
A9: Total Capex per Subscriber | B9: =SUM(B6:B8) | C9: =SUM(C6:C8) | D9: =B9-C9 | E9: Hardware Subsidy | F9: Total Capex absorbed per Household
A11: 2. ONE-TIME CUSTOMER ACQUISITION COSTS (CAC)
A12: Acquisition Cost Item | B12: Bulk/Unit Cost (₹) | C12: Charge to Customer (₹) | D12: Net Altura CAC (₹) | E12: Channel Mapped | F12: Acquisition Channel Efficiency Justification
A13: Technician Labor Cost | B13: 300 | C13: 0 | D13: 300 | E13: In-Home Service Engineers | F13: Cost of initial physical visit and hardware deployment
A14: Physical SIM Card & Security Chip | B14: 80 | C14: 0 | D14: 80 | E14: Outbound Delivery | F14: Provisioning costs for 2 family postpaid SIM cards
A15: MNP Switcher Cashback (Rebate) | B15: 500 | C15: 0 | D15: 500 | E15: Outbound MNP | F15: Buyout penalty fee rebate given to Jio/Vi switcher on first bill
A16: Doorstep MNP Delivery Runner | B16: 100 | C16: 0 | D16: 100 | E16: Outbound Delivery | F16: Runner cost for doorstep delivery and SIM activation in 15 mins
A17: Technician MNP Porting Commission | B17: 50 | C17: 0 | D17: 50 | E17: In-Home Service Engineers | F17: Engineers get bonus incentive to check competitor SIMs and execute porting
A18: Blended Marketing/Advertising Spend | B18: 500 | C18: 0 | D18: 500 | E18: Digital Portal / OOH | F18: Pincode-targeted search ads, billboards, and performance marketing
A19: Total CAC per Subscriber | B19: =SUM(B13:B18) | C19: =SUM(C13:C18) | D19: =B19-C19 | E19: Ecosystem Outbound CAC | F19: Total acquisition CAC outlay per customer
A21: 3. MONTHLY RECURRING OPERATIONAL COSTS (OPEX)
A22: Opex Cost Item | B22: Monthly Cost (₹) | C22: Zebra Mapped Product | D22: EBITDA Mapped Segment | E22: EBITDA Margin Context | F22: Operational Performance Moat Justification
A23: Broadband Backhaul Bandwidth | B23: 100 | C23: Fiber Broadband | D23: Broadband (32% EBITDA) | E23: Incremental bandwidth cost of laying and servicing fiber lines | F23: Home fiber link connection backhaul and hardware maintenance
A24: Cellular Network Data Pool (2 SIMs) | B24: 160 | C24: Postpaid Mobile | D24: Mobility (28% EBITDA) | E24: Core cellular tower maintenance and pool data routing | F24: Postpaid cell pool, priority network routing slot
A25: DTH Carriage & Content Licensing | B25: 120 | C25: Xstream Play TV | D25: DTH / TV (12% EBITDA) | E25: Content carriage licensing fee paid to broadcasters/OTT players | F25: 4K TV feed, basic channels, carriage, and OTT app licenses
A26: Google One Bulk License Royalty | B26: 50 | C26: Google One (200GB) | D26: N/A (Net 15% Margin) | E26: Wholesale bulk storage royalty fee paid directly to Google | F26: 200GB cloud storage space, family backup cloud access
A27: Xsafe Camera Cloud Storage Hosting | B27: 40 | C27: Xsafe Smart Camera | D27: Surveillance (35% EBITDA) | E27: AWS/Azure cloud hosting cost per camera cloud recording feed | F27: 7-day recording loop storage space and humanoid alert notification
A28: Payments Bank Administration Fee | B28: 15 | C28: Payments Bank | D28: Banking (50% EBITDA) | E28: Transaction clearing, database administration, and KYC cost | F28: 7% interest rate margin management, Safe Pay anti-fraud engine
A29: Thanks Coins Loyalty Redemption | B29: 50 | C29: Ecosystem Reward | D29: Ecosystem Loyalty | E29: Margin cost of coin redemptions at retail partner merchants | F29: Loyalty coins program, incentivizing Autopay and monthly renewals
A30: Total Recurring Monthly Opex | B30: =SUM(B23:B29) | C30: Combined Services | D30: Weighted Segments | E30: EBITDA Profit Factor | F30: Altura's total monthly operational cost per user

Sheet 24-Month Projections
A1: COHORT BUDGETING & PAYBACK CASH FLOW MODEL (1,000 SWITCHERS)
A3: MONTH-BY-MONTH REVENUES, EXPENSES, EBITDA AND CUMULATIVE PAYBACK SIMULATION
A4: Timeline Month | B4: Active Customers | C4: Pricing Tier / Period | D4: Cohort Revenue (₹) | E4: Cohort Recurring Opex (₹) | F4: One-Time Capex + CAC Outlay (₹) | G4: EBITDA Profit/Loss (₹) | H4: Cumulative Cash Flow (₹)
A5: Month 0 (Acquisition) | B5: 1000 | C5: Ecosystem Setup & CAC Outflow | D5: 0 | E5: 0 | F5: =B5*('Detailed Cost Breakdown'!D9+'Detailed Cost Breakdown'!D19) | G5: =-F5 | H5: =G5
A6: Month 1 | B6: =B5*(1-(0.05/12)) | C6: Promo Pricing (₹999/mo) | D6: =B6*(999-50) | E6: =B6*'Detailed Cost Breakdown'!B30 | F6: 0 | G6: =D6-E6 | H6: =H5+G6
A7: Month 2 | B7: =B6*(1-(0.05/12)) | C7: Promo Pricing (₹999/mo) | D7: =B7*(999-50) | E7: =B7*'Detailed Cost Breakdown'!B30 | F7: 0 | G7: =D7-E7 | H7: =H6+G7
A8: Month 3 | B8: =B7*(1-(0.05/12)) | C8: Promo Pricing (₹999/mo) | D8: =B8*(999-50) | E8: =B8*'Detailed Cost Breakdown'!B30 | F8: 0 | G8: =D8-E8 | H8: =H7+G8
A9: Month 4 | B9: =B8*(1-(0.05/12)) | C9: Standard Bundle (₹1,499/mo) | D9: =B9*(1499-50) | E9: =B9*'Detailed Cost Breakdown'!B30 | F9: 0 | G9: =D9-E9 | H9: =H8+G9
A10: Month 5 | B10: =B9*(1-(0.05/12)) | C10: Standard Bundle (₹1,499/mo) | D10: =B10*(1499-50) | E10: =B10*'Detailed Cost Breakdown'!B30 | F10: 0 | G10: =D10-E10 | H10: =H9+G10
A11: Month 6 | B11: =B10*(1-(0.05/12)) | C11: Standard Bundle (₹1,499/mo) | D11: =B11*(1499-50) | E11: =B11*'Detailed Cost Breakdown'!B30 | F11: 0 | G11: =D11-E11 | H11: =H10+G11
A12: Month 7 | B12: =B11*(1-(0.05/12)) | C12: Standard Bundle (₹1,499/mo) | D12: =B12*(1499-50) | E12: =B12*'Detailed Cost Breakdown'!B30 | F12: 0 | G12: =D12-E12 | H12: =H11+G12
A13: Month 8 | B13: =B12*(1-(0.05/12)) | C13: Standard Bundle (₹1,499/mo) | D13: =B13*(1499-50) | E13: =B13*'Detailed Cost Breakdown'!B30 | F13: 0 | G13: =D13-E13 | H13: =H12+G13
A14: Month 9 (PAYBACK BREAK-EVEN) | B14: =B13*(1-(0.05/12)) | C14: Standard Bundle (₹1,499/mo) | D14: =B14*(1499-50) | E14: =B14*'Detailed Cost Breakdown'!B30 | F14: 0 | G14: =D14-E14 | H14: =H13+G14
A15: Month 10 | B15: =B14*(1-(0.05/12)) | C15: Standard Bundle (₹1,499/mo) | D15: =B15*(1499-50) | E15: =B15*'Detailed Cost Breakdown'!B30 | F15: 0 | G15: =D15-E15 | H15: =H14+G15
A16: Month 11 | B16: =B15*(1-(0.05/12)) | C16: Standard Bundle (₹1,499/mo) | D16: =B16*(1499-50) | E16: =B16*'Detailed Cost Breakdown'!B30 | F16: 0 | G16: =D16-E16 | H16: =H15+G16
A17: Month 12 | B17: =B16*(1-(0.05/12)) | C17: Standard Bundle (₹1,499/mo) | D17: =B17*(1499-50) | E17: =B17*'Detailed Cost Breakdown'!B30 | F17: 0 | G17: =D17-E17 | H17: =H16+G17
A18: Month 13 | B18: =B17*(1-(0.05/12)) | C18: Standard Bundle (₹1,499/mo) | D18: =B18*(1499-50) | E18: =B18*'Detailed Cost Breakdown'!B30 | F18: 0 | G18: =D18-E18 | H18: =H17+G18
A19: Month 14 | B19: =B18*(1-(0.05/12)) | C19: Standard Bundle (₹1,499/mo) | D19: =B19*(1499-50) | E19: =B19*'Detailed Cost Breakdown'!B30 | F19: 0 | G19: =D19-E19 | H19: =H18+G19
A20: Month 15 | B20: =B19*(1-(0.05/12)) | C20: Standard Bundle (₹1,499/mo) | D20: =B20*(1499-50) | E20: =B20*'Detailed Cost Breakdown'!B30 | F20: 0 | G20: =D20-E20 | H20: =H19+G20
A21: Month 16 | B21: =B20*(1-(0.05/12)) | C21: Standard Bundle (₹1,499/mo) | D21: =B21*(1499-50) | E21: =B21*'Detailed Cost Breakdown'!B30 | F21: 0 | G21: =D21-E21 | H21: =H20+G21
A22: Month 17 | B22: =B21*(1-(0.05/12)) | C22: Standard Bundle (₹1,499/mo) | D22: =B22*(1499-50) | E22: =B22*'Detailed Cost Breakdown'!B30 | F22: 0 | G22: =D22-E22 | H22: =H21+G22
A23: Month 18 | B23: =B22*(1-(0.05/12)) | C23: Standard Bundle (₹1,499/mo) | D23: =B23*(1499-50) | E23: =B23*'Detailed Cost Breakdown'!B30 | F23: 0 | G23: =D23-E23 | H23: =H22+G23
A24: Month 19 | B24: =B23*(1-(0.05/12)) | C24: Standard Bundle (₹1,499/mo) | D24: =B24*(1499-50) | E24: =B24*'Detailed Cost Breakdown'!B30 | F24: 0 | G24: =D24-E24 | H24: =H23+G24
A25: Month 20 | B25: =B24*(1-(0.05/12)) | C25: Standard Bundle (₹1,499/mo) | D25: =B25*(1499-50) | E25: =B25*'Detailed Cost Breakdown'!B30 | F25: 0 | G25: =D25-E25 | H25: =H24+G25
A26: Month 21 | B26: =B25*(1-(0.05/12)) | C26: Standard Bundle (₹1,499/mo) | D26: =B26*(1499-50) | E26: =B26*'Detailed Cost Breakdown'!B30 | F26: 0 | G26: =D26-E26 | H26: =H25+G26
A27: Month 22 | B27: =B26*(1-(0.05/12)) | C27: Standard Bundle (₹1,499/mo) | D27: =B27*(1499-50) | E27: =B27*'Detailed Cost Breakdown'!B30 | F27: 0 | G27: =D27-E27 | H27: =H26+G27
A28: Month 23 | B28: =B27*(1-(0.05/12)) | C28: Standard Bundle (₹1,499/mo) | D28: =B28*(1499-50) | E28: =B28*'Detailed Cost Breakdown'!B30 | F28: 0 | G28: =D28-E28 | H28: =H27+G28
A29: Month 24 | B29: =B28*(1-(0.05/12)) | C29: Standard Bundle (₹1,499/mo) | D29: =B29*(1499-50) | E29: =B29*'Detailed Cost Breakdown'!B30 | F29: 0 | G29: =D29-E29 | H29: =H28+G29
A32: Development Cost Amortization | B32: =-'Detailed Cost Breakdown'!D5 | G32: Total Cohort Net Profit | H32: =H29+B32

Sheet Competitor & Elasticity
A1: COMPETITOR MAPPING & CONJOINT PRICE ELASTICITY
A3: PRIMARY RESEARCH CONJOINT VALUE MODEL (N=132)
A4: Bundle Plan Option | B4: Monthly Price Point (₹) | C4: Respondent Acceptance % | D4: Monthly Revenue Yield (₹) | E4: Financial Suitability / Sweet Spot Analysis
A5: Altura Starter | B5: 499 | C5: 0.82 | D5: =B5*C5 | E5: High acceptance for entry-level; limited monetization capability
A6: Altura Connect | B6: 999 | C6: 0.68 | D6: =B6*C6 | E6: Steady standard tier; good for couples and smaller households
A7: Family Secure (Promo) | B7: 999 | C7: 0.89 | D7: =B7*C7 | E7: OPTIMAL SWEET SPOT: Lifts acceptance by 111% vs. standard price
A8: Family Secure (Standard) | B8: 1499 | C8: 0.42 | D8: =B8*C8 | E8: High long-term ARPU but requires promo introductory hook to convert
A9: Altura Infinite | B9: 2999 | C9: 0.15 | D9: =B9*C9 | E9: Niche high-value play; generates premium ARPU from 15% of market
A12: COMPETITOR CONVERGENCE OFFERING COMPARISON
A13: Convergence Metric | B13: Reliance Jio (Broadband-first) | C13: Vodafone Idea (Vi) (No Fiber) | D13: Altura Communications (Ours)
A14: Core Convergence Offer | B14: Broadband + TV + OTT bundles | C14: Partnership-only (No owned Fiber) | D14: Broadband + TV + Mobile SIMs + Bank + Security
A15: Entry Price Point | B15: ₹399/mo (standalone fiber) | C15: N/A (mobile only) | D15: ₹499/mo (Starter Bundle)
A16: Home Security integration | B16: JioFiber smart camera (unintegrated app) | C16: No home security products | D16: Altura Xsafe camera with cellular failover backup
A17: Loyalty Rewards | B17: JioPrime coupon tie-ups | C17: Vi Rewards app checkouts | D17: Altura Thanks Coins (integrated bill cashbacks)
A18: Financial Integration | B18: UPI Payments wallet | C18: Paytm/Third-party tie-ups | D18: Altura Payments Bank (7% interest & Safe Pay)
