Workbook

Sheet Dashboard & Summary
A1: ALTURA HOUSEHOLD CONVERGENCE STRATEGY FEASIBILITY DASHBOARD
A3: CONVERGENCE ACQUISITION VS. BASE CONVERSION SIDE-BY-SIDE COMPARISON
A4: Feasibility Metric | B4: Outbound Poaching (Jio/Vi Switchers) | C4: Segment A (Mobile-Only Base) | D4: Segment B (Broadband-Only Base) | E4: Segment C (Double-Play Standalone) | F4: Revenue / Retention Multiplier | G4: Strategic Modeling Justification
A5: Upfront Hardware Capex per Subscriber | B5: 4800 | C5: 4800 | D5: 3300 | E5: 3300 | F5: Amortized asset base | G5: ONT Router (₹1,500) + TV Box (₹1,800) + Camera (₹1,500); Segment B/C reuse existing router ONT
A6: Upfront Sales & MNP CAC per Subscriber | B6: 1530 | C6: 400 | D6: 1130 | E6: 400 | F6: CAC cost savings | G6: Outbound requires ads, runner, tech commission & ₹500 rebate; Segment B requires mobile MNP port-in
A7: Total Upfront Investment per Subscriber | B7: =B5+B6 | C7: =C5+C6 | D7: =D5+D6 | E7: =E5+E6 | F7: Initial layout per HH | G7: Combined CapEx + CAC absorbed by Altura to remove subscriber migration friction
A8: First-Bill Customer Switcher Cashback | B8: 500 | C8: 0 | D8: 500 | E8: 0 | F8: Waived for existing mobile | G8: One-time contract buyout rebate credited on first bill; ₹0 for existing Altura mobile accounts
A9: Monthly Net Revenue (Promo, Mos 1-3) | B9: 949 | C9: 949 | D9: 949 | E9: 949 | F9: 1.00x Promo ARPU | G9: ₹999 promotional price minus ₹50 Autopay discount (waived entry barrier)
A10: Monthly Net Revenue (Standard, Mos 4+) | B10: 1449 | C10: 1449 | D10: 1449 | E10: 1449 | F10: 1.12x ARPU increase | G10: ₹1,499 standard Family Secure price minus ₹50 Autopay discount
A11: Weighted Recurring Monthly Opex | B11: 535 | C11: 535 | D11: 535 | E11: 535 | F11: Highly scalable network | G11: Includes bandwidth backhaul, postpaid pool, Google One, AWS camera cloud, bank, & loyalty program
A12: Monthly EBITDA Margin (Standard Period) | B12: 0.6308 | C12: 0.6308 | D12: 0.6308 | E12: 0.6308 | F12: 63.1% EBITDA Margin | G12: High operating margin once initial customer-end hardware is capitalized and amortized
A13: Average Customer Relationship (Years) | B13: 20 | C13: 20 | D13: 20 | E13: 20 | F13: 4.44x Churn Arbitrage | G13: Bundle reduces annual churn from 22.0% (standalone) to 5.0% (triple-play)
A14: Payback Break-Even Period (Months) | B14: 8.57 | C14: 7.33 | D14: 6.49 | E14: 5.69 | F14: Saves up to 3.0 months | G14: Time to recover initial hardware subsidy + CAC outlay; existing base conversions pay back significantly faster
A15: Net EBITDA Lifetime Value (LTV) | B15: 97511 | C15: 98411 | D15: 98411 | E15: 98411 | F15: 4.82x EBITDA Multiplier | G15: Consolidated household LTV net of CAC vs. stand-alone mobile/broadband LTV (₹20,226)
A16: Ecosystem Return on Investment (ROI) | B16: 15.4 | C16: 18.9 | D16: 22.2 | E16: 26.6 | F16: Up to 26.6x Lifetime return | G16: EBITDA Lifetime contribution divided by total initial Capex + CAC outlay
A19: STRATEGIC SLIDE PITCH KEY DATA POINTS
A20: Slide Focus | B20: Key Data Point to Present | C20: Strategic Takeaway for Judges
A21: Slide 2: Solution Engine | B21: Inbound-First Base Conversion Strategy | C21: Saves up to ₹2,630 in upfront router and SIM marketing CAC by targeting existing high-trust customers first.
A22: Slide 3: Financial Feasibility | B22: Segment C Payback = 5.7 Months (ROI = 26.6x) | C22: Consolidating existing double-play subscribers only requires a ₹3.7k TV/Camera outlay, returning ₹98k in lifetime EBITDA.
A23: Slide 3: Financial Feasibility | B23: Average Base Payback = 6.5 Months | C23: Waiving upfront hardware and charging ₹999 promo price is highly feasible, recovering investments 2.1 months faster than outbound poaching.

Sheet Slide Contents
A1: POWERPOINT PRESENTATION SLIDE CONTENTS
A3: Slide Reference | B3: Content Heading | C3: Sub-headline / Context | D3: Bullet Point Content | E3: Key Strategic Takeaway
A4: Slide 2: Solution | B4: Altura Home: The Strategy in Action (Organic Base Conversion + Outbound Poaching) | C4: Leveraging organic single-play and double-play subscriber bases as the primary high-retention launch pad, while positioning outbound competitor poaching as a secondary future lever. | D4: 1. Focus on Converting Our Own Base First: - Inbound Cross-Selling: Target existing Mobile postpaid-only, Broadband-only, and standalone Double-Play customers to upgrade them to Family Secure. - Lower Entry Barrier: Waiving router costs for existing broadband accounts and SIM card provisioning for existing mobile lines reduces initial layout. - Trust & Stickiness: Converting our own base drives higher immediate trust and locks in multiple services under a single unified billing portal. 2. The Onboarding Portal & Web Tools: - Build-Your-Own-Bundle Customizer: Interactive calculator showing real-time monthly billing savings and Thanks Coins to dismantle Utility-Arbitrage Bias. - AirBot AI digital concierge to simplify profile matching and eliminate onboarding friction. 3. Outbound Competitor Poaching (Secondary Future Lever): - Doorstep MNP in 15 Minutes: Eqquiping in-home installation technicians with mobile activation apps to execute MNP port-ins. - Switcher's Contract Rebate: One-time ₹500 cashback credit to offset switcher penalty fees. | E4: Targeting our own base first eliminates the largest Capex and marketing CAC costs, securing maximum value before expanding outbound.
A5: Slide 3: Feasibility | B5: Illustrative Financial Feasibility (Based on industry benchmarks and internal modeling assumptions) | C5: Amortizing upfront development, hardware subsidy, and switcher rebates through high-retention monthly recurring EBITDA margins. | D5: 1. Existing Base Conversion Economics (Highest Return Loop): - Segment A (Mobile-Only Base): Initial outlay ₹5,200 (Router/TV Box/Camera/Labor/Upsell) -> Payback = 7.3 Months (ROI = 18.9x). - Segment B (Broadband-Only Base): Initial outlay ₹4,430 (reuses existing router, adds mobile SIM MNP/TV/Camera) -> Payback = 6.5 Months (ROI = 22.2x). - Segment C (Double-Play Standalone): Initial outlay ₹3,700 (reuses existing router & postpaid SIMs, adds TV/Camera/Labor) -> Payback = 5.7 Months (ROI = 26.6x). - Weighted Base Payback: Average of 6.5 Months (2.1 months faster than outbound competitor poaching). 2. Detailed Operating Cost & LTV Benchmarks: - Recurring monthly Opex: ₹535/mo per user (bandwidth, content licensing, cellular tower pool, Google bulk royalty, cloud storage, bank administration). - Google One (200GB): Modeled as an assumed volume-negotiated enterprise licensing rate (wholesale bulk transfer pricing rather than retail). - Churn Arbitrage LTV: Consolidating services reduces annual churn from 22.0% (standalone) to 5.0% (bundled), extending relationship lifetime from 4.5 to 20 years, yielding ₹98,411 Lifetime EBITDA contribution. | E5: waiving hardware and contract buyout costs is highly feasible, returning the initial layouts in 5.7 to 7.3 months for our own base.

Sheet Illustrative Cost Breakdown
A1: ILLUSTRATIVE UNIT ECONOMICS & MODELING ASSUMPTIONS
A3: 1. ONE-TIME CAPITAL & DEVELOPMENT COSTS (CAPEX - ASSUMED)
A4: Cost Item | B4: Bulk Procurement Price (₹) | C4: Customer Charging (₹) | D4: Net Altura Subsidy (₹) | E4: Amortization Rule | F4: Strategic Business Justification
A5: Website & AI Portal Development | B5: 2000000 | C5: 0 | D5: 2000000 | E5: Amortized over first 1,000 cohort (₹2,000/HH) | F5: Design, customizer custom frontend, AirBot AI NLP training, APIs
A6: Dual-Band ONT Wi-Fi Router | B6: 1500 | C6: 0 | D6: 1500 | E6: Amortized over customer contract lifetime | F6: Waived to eliminate migration barrier; high-speed home connectivity anchor
A7: Altura Xstream 4K Smart Android Box | B7: 1800 | C7: 0 | D7: 1800 | E7: Amortized over customer contract lifetime | F7: Waived; hybrid satellite/OTT television anchor to stop DTH revenue drop
A8: Altura Xsafe AI Smart Security Camera | B8: 1500 | C8: 0 | D8: 1500 | E8: Amortized over customer contract lifetime | F8: Waived; smart home security camera enlisting cell-failover backup tech
A9: Total Capex per Subscriber | B9: =SUM(B6:B8) | C9: =SUM(C6:C8) | D9: =B9-C9 | E9: Hardware Subsidy | F9: Total Capex absorbed per Household
A11: 2. ONE-TIME CUSTOMER ACQUISITION COSTS (CAC - ASSUMED)
A12: Acquisition Cost Item | B12: Bulk/Unit Cost (₹) | C12: Charge to Customer (₹) | D12: Net Altura CAC (₹) | E12: Channel Mapped | F12: Acquisition Channel Efficiency Justification
A13: Technician Labor Cost | B13: 300 | C13: 0 | D13: 300 | E13: In-Home Service Engineers | F13: Cost of initial physical visit and hardware deployment
A14: Physical SIM Card & Security Chip | B14: 80 | C14: 0 | D14: 80 | E14: Outbound Delivery | F14: Provisioning costs for 2 family postpaid SIM cards
A15: MNP Switcher Cashback (Rebate) | B15: 500 | C15: 0 | D15: 500 | E15: Outbound MNP | F15: Buyout penalty fee rebate given to Jio/Vi switcher on first bill
A16: Doorstep MNP Delivery Runner | B16: 100 | C16: 0 | D16: 100 | E16: Outbound Delivery | F16: Runner cost for doorstep delivery and SIM activation in 15 mins
A17: Technician MNP Porting Commission | B17: 50 | C17: 0 | D17: 50 | E17: In-Home Service Engineers | F17: Engineers get bonus incentive to check competitor SIMs and execute porting
A18: Blended Marketing/Advertising Spend | B18: 500 | C18: 0 | D18: 500 | E18: Digital Portal / OOH | F18: Pincode-targeted search ads, billboards, and performance marketing
A19: Total CAC per Subscriber | B19: =SUM(B13:B18) | C19: =SUM(C13:C18) | D19: =B19-C19 | E19: Ecosystem Outbound CAC | F19: Total acquisition CAC outlay per customer
A21: 3. MONTHLY RECURRING OPERATIONAL COSTS (OPEX - ASSUMED)
A22: Opex Cost Item | B22: Monthly Cost (₹) | C22: Zebra Mapped Product | D22: EBITDA Mapped Segment | E22: EBITDA Margin Context | F22: Operational Performance Moat Justification
A23: Broadband Backhaul Bandwidth | B23: 100 | C23: Fiber Broadband | D23: Broadband (32% EBITDA) | E23: Incremental bandwidth cost of laying and servicing fiber lines | F23: Home fiber link connection backhaul and hardware maintenance
A24: Cellular Network Data Pool (2 SIMs) | B24: 160 | C24: Postpaid Mobile | D24: Mobility (28% EBITDA) | E24: Core cellular tower maintenance and pool data routing | F24: Postpaid cell pool, priority network routing slot
A25: DTH Carriage & Content Licensing | B25: 120 | C25: Xstream Play TV | D25: DTH / TV (12% EBITDA) | E25: Content carriage licensing fee paid to broadcasters/OTT players | F25: 4K TV feed, basic channels, carriage, and OTT app licenses
A26: Google One Bulk License Royalty | B26: 50 | C26: Google One (200GB) | D26: N/A (Net 15% Margin) | E26: Assumed volume-negotiated enterprise licensing cost (Airtel offers 100GB/6-mos; Altura negotiates 200GB wholesale) | F26: 200GB cloud storage space, family backup cloud access
A27: Xsafe Camera Cloud Storage Hosting | B27: 40 | C27: Xsafe Smart Camera | D27: Surveillance (35% EBITDA) | E27: AWS/Azure cloud hosting cost per camera cloud recording feed | F27: 7-day recording loop storage space and humanoid alert notification
A28: Payments Bank Administration Fee | B28: 15 | C28: Payments Bank | D28: Banking (50% EBITDA) | E28: Transaction clearing, database administration, and KYC cost | F28: 7% interest rate margin management, Safe Pay anti-fraud engine
A29: Thanks Coins Loyalty Redemption | B29: 50 | C29: Ecosystem Reward | D29: Ecosystem Loyalty | E29: Margin cost of coin redemptions at retail partner merchants | F29: Loyalty coins program, incentivizing Autopay and monthly renewals
A30: Total Recurring Monthly Opex | B30: =SUM(B23:B29) | C30: Combined Services | D30: Weighted Segments | E30: EBITDA Profit Factor | F30: Altura's total monthly operational cost per user

Sheet Existing Base Conversion
A1: ORGANIC CUSTOMER BASE CONVERSION BUDGETS (COHORTS OF 1,000)
A3: MONTH-BY-MONTH RECOVERY TIMELINES AND CUMULATIVE EBITDA BY SEGMENT
A4: Timeline | B4: Segment A: Active | C4: Segment A: Cash (₹) | D4: Segment B: Active | E4: Segment B: Cash (₹) | F4: Segment C: Active | G4: Segment C: Cash (₹) | H4: Upsell Period & Pricing Details
A5: Month 0 (Upfront) | B5: 1000 | C5: =-B5*'Dashboard & Summary'!C7 | D5: 1000 | E5: =-D5*'Dashboard & Summary'!D7 | F5: 1000 | G5: =-F5*'Dashboard & Summary'!E7 | H5: Hardware subsidies + Digital Upsell labor
A6: Month 1 | B6: =B5*(1-(0.05/12)) | C6: =C5+(B6*414) | D6: =D5*(1-(0.05/12)) | E6: =E5+(D6*414) | F6: =F5*(1-(0.05/12)) | G6: =G5+(F6*414) | H6: Promo Pricing (₹949 Net)
A7: Month 2 | B7: =B6*(1-(0.05/12)) | C7: =C6+(B7*414) | D7: =D6*(1-(0.05/12)) | E7: =E6+(D7*414) | F7: =F6*(1-(0.05/12)) | G7: =G6+(F7*414) | H7: Promo Pricing (₹949 Net)
A8: Month 3 | B8: =B7*(1-(0.05/12)) | C8: =C7+(B8*414) | D8: =D7*(1-(0.05/12)) | E8: =E7+(D8*414) | F8: =F7*(1-(0.05/12)) | G8: =G7+(F8*414) | H8: Promo Pricing (₹949 Net)
A9: Month 4 | B9: =B8*(1-(0.05/12)) | C9: =C8+(B9*914) | D9: =D8*(1-(0.05/12)) | E9: =E8+(D9*914) | F9: =F8*(1-(0.05/12)) | G9: =G8+(F9*914) | H9: Standard pricing (₹1,449 Net)
A10: Month 5 | B10: =B9*(1-(0.05/12)) | C10: =C9+(B10*914) | D10: =D9*(1-(0.05/12)) | E10: =E9+(D10*914) | F10: =F9*(1-(0.05/12)) | G10: =G9+(F10*914) | H10: Standard pricing (₹1,449 Net)
A11: Month 6 | B11: =B10*(1-(0.05/12)) | C11: =C10+(B11*914) | D11: =D10*(1-(0.05/12)) | E11: =E10+(D11*914) | F11: =F10*(1-(0.05/12)) | G11: =G10+(F11*914) | H11: Standard pricing (₹1,449 Net)
A12: Month 7 | B12: =B11*(1-(0.05/12)) | C12: =C11+(B12*914) | D12: =D11*(1-(0.05/12)) | E12: =E11+(D12*914) | F12: =F11*(1-(0.05/12)) | G12: =G11+(F12*914) | H12: Standard pricing (₹1,449 Net)
A13: Month 8 | B13: =B12*(1-(0.05/12)) | C13: =C12+(B13*914) | D13: =D12*(1-(0.05/12)) | E13: =E12+(D13*914) | F13: =F12*(1-(0.05/12)) | G13: =G12+(F13*914) | H13: Standard pricing (₹1,449 Net)
A14: Month 9 | B14: =B13*(1-(0.05/12)) | C14: =C13+(B14*914) | D14: =D13*(1-(0.05/12)) | E14: =E13+(D14*914) | F14: =F13*(1-(0.05/12)) | G14: =G13+(F14*914) | H14: Standard pricing (₹1,449 Net)
A15: Month 10 | B15: =B14*(1-(0.05/12)) | C15: =C14+(B15*914) | D15: =D14*(1-(0.05/12)) | E15: =E14+(D15*914) | F15: =F14*(1-(0.05/12)) | G15: =G14+(F15*914) | H15: Standard pricing (₹1,449 Net)
A16: Month 11 | B16: =B15*(1-(0.05/12)) | C16: =C15+(B16*914) | D16: =D15*(1-(0.05/12)) | E16: =E15+(D16*914) | F16: =F15*(1-(0.05/12)) | G16: =G15+(F16*914) | H16: Standard pricing (₹1,449 Net)
A17: Month 12 | B17: =B16*(1-(0.05/12)) | C17: =C16+(B17*914) | D17: =D16*(1-(0.05/12)) | E17: =E16+(D17*914) | F17: =F16*(1-(0.05/12)) | G17: =G16+(F17*914) | H17: Standard pricing (₹1,449 Net)
A18: Month 13 | B18: =B17*(1-(0.05/12)) | C18: =C17+(B18*914) | D18: =D17*(1-(0.05/12)) | E18: =E17+(D18*914) | F18: =F17*(1-(0.05/12)) | G18: =G17+(F18*914) | H18: Standard pricing (₹1,449 Net)
A19: Month 14 | B19: =B18*(1-(0.05/12)) | C19: =C18+(B19*914) | D19: =D18*(1-(0.05/12)) | E19: =E18+(D19*914) | F19: =F18*(1-(0.05/12)) | G19: =G18+(F19*914) | H19: Standard pricing (₹1,449 Net)
A20: Month 15 | B20: =B19*(1-(0.05/12)) | C20: =C19+(B20*914) | D20: =D19*(1-(0.05/12)) | E20: =E19+(D20*914) | F20: =F19*(1-(0.05/12)) | G20: =G19+(F20*914) | H20: Standard pricing (₹1,449 Net)
... A29: Month 24 | B29: =B28*(1-(0.05/12)) | C29: =C28+(B29*914) | D29: =D28*(1-(0.05/12)) | E29: =E28+(D29*914) | F29: =F28*(1-(0.05/12)) | G29: =G28+(F29*914) | H29: Standard pricing (₹1,449 Net)

Sheet Outbound Cohort Projections
A1: COHORT BUDGETING & PAYBACK CASH FLOW MODEL (1,000 SWITCHERS)
A3: MONTH-BY-MONTH REVENUES, EXPENSES, EBITDA AND CUMULATIVE PAYBACK SIMULATION
A4: Timeline Month | B4: Active Customers | C4: Pricing Tier / Period | D4: Cohort Revenue (₹) | E4: Cohort Recurring Opex (₹) | F4: One-Time Capex + CAC Outlay (₹) | G4: EBITDA Profit/Loss (₹) | H4: Cumulative Cash Flow (₹)
A5: Month 0 (Acquisition) | B5: 1000 | C5: Ecosystem Setup & CAC Outflow | D5: 0 | E5: 0 | F5: =B5*('Illustrative Cost Breakdown'!D9+'Illustrative Cost Breakdown'!D19) | G5: =-F5 | H5: =G5
A6: Month 1 | B6: =B5*(1-(0.05/12)) | C6: Promo Pricing (₹999/mo) | D6: =B6*(999-50) | E6: =B6*'Illustrative Cost Breakdown'!B30 | F6: 0 | G6: =D6-E6 | H6: =H5+G6
A7: Month 2 | B7: =B6*(1-(0.05/12)) | C7: Promo Pricing (₹999/mo) | D7: =B7*(999-50) | E7: =B7*'Illustrative Cost Breakdown'!B30 | F7: 0 | G7: =D7-E7 | H7: =H6+G7
A8: Month 3 | B8: =B7*(1-(0.05/12)) | C8: Promo Pricing (₹999/mo) | D8: =B8*(999-50) | E8: =B8*'Illustrative Cost Breakdown'!B30 | F8: 0 | G8: =D8-E8 | H8: =H7+G8
A9: Month 4 | B9: =B8*(1-(0.05/12)) | C9: Standard Bundle (₹1,499/mo) | D9: =B9*(1499-50) | E9: =B9*'Illustrative Cost Breakdown'!B30 | F9: 0 | G9: =D9-E9 | H9: =H8+G9
A10: Month 5 | B10: =B9*(1-(0.05/12)) | C10: Standard Bundle (₹1,499/mo) | D10: =B10*(1499-50) | E10: =B10*'Illustrative Cost Breakdown'!B30 | F10: 0 | G10: =D10-E10 | H10: =H9+G10
A11: Month 6 | B11: =B10*(1-(0.05/12)) | C11: Standard Bundle (₹1,499/mo) | D11: =B11*(1499-50) | E11: =B11*'Illustrative Cost Breakdown'!B30 | F11: 0 | G11: =D11-E11 | H11: =H10+G11
A12: Month 7 | B12: =B11*(1-(0.05/12)) | C12: Standard Bundle (₹1,499/mo) | D12: =B12*(1499-50) | E12: =B12*'Illustrative Cost Breakdown'!B30 | F12: 0 | G12: =D12-E12 | H12: =H11+G12
A13: Month 8 | B13: =B12*(1-(0.05/12)) | C13: Standard Bundle (₹1,499/mo) | D13: =B13*(1499-50) | E13: =B13*'Illustrative Cost Breakdown'!B30 | F13: 0 | G13: =D13-E13 | H13: =H12+G13
A14: Month 9 (PAYBACK BREAK-EVEN) | B14: =B13*(1-(0.05/12)) | C14: Standard Bundle (₹1,499/mo) | D14: =B14*(1499-50) | E14: =B14*'Illustrative Cost Breakdown'!B30 | F14: 0 | G14: =D14-E14 | H14: =H13+G14
A15: Month 10 | B15: =B14*(1-(0.05/12)) | C15: Standard Bundle (₹1,499/mo) | D15: =B15*(1499-50) | E15: =B15*'Illustrative Cost Breakdown'!B30 | F15: 0 | G15: =D15-E15 | H15: =H14+G15
A16: Month 11 | B16: =B15*(1-(0.05/12)) | C16: Standard Bundle (₹1,499/mo) | D16: =B16*(1499-50) | E16: =B16*'Illustrative Cost Breakdown'!B30 | F16: 0 | G16: =D16-E16 | H16: =H15+G16
A17: Month 12 | B17: =B16*(1-(0.05/12)) | C17: Standard Bundle (₹1,499/mo) | D17: =B17*(1499-50) | E17: =B17*'Illustrative Cost Breakdown'!B30 | F17: 0 | G17: =D17-E17 | H17: =H16+G17
A18: Month 13 | B18: =B17*(1-(0.05/12)) | C18: Standard Bundle (₹1,499/mo) | D18: =B18*(1499-50) | E18: =B18*'Illustrative Cost Breakdown'!B30 | F18: 0 | G18: =D18-E18 | H18: =H17+G18
A19: Month 14 | B19: =B18*(1-(0.05/12)) | C19: Standard Bundle (₹1,499/mo) | D19: =B19*(1499-50) | E19: =B19*'Illustrative Cost Breakdown'!B30 | F19: 0 | G19: =D19-E19 | H19: =H18+G19
A20: Month 15 | B20: =B19*(1-(0.05/12)) | C20: Standard Bundle (₹1,499/mo) | D20: =B20*(1499-50) | E20: =B20*'Illustrative Cost Breakdown'!B30 | F20: 0 | G20: =D20-E20 | H20: =H19+G20
A21: Month 16 | B21: =B20*(1-(0.05/12)) | C21: Standard Bundle (₹1,499/mo) | D21: =B21*(1499-50) | E21: =B21*'Illustrative Cost Breakdown'!B30 | F21: 0 | G21: =D21-E21 | H21: =H20+G21
A22: Month 17 | B22: =B21*(1-(0.05/12)) | C22: Standard Bundle (₹1,499/mo) | D22: =B22*(1499-50) | E22: =B22*'Illustrative Cost Breakdown'!B30 | F22: 0 | G22: =D22-E22 | H22: =H21+G22
A23: Month 18 | B23: =B22*(1-(0.05/12)) | C23: Standard Bundle (₹1,499/mo) | D23: =B23*(1499-50) | E23: =B23*'Illustrative Cost Breakdown'!B30 | F23: 0 | G23: =D23-E23 | H23: =H22+G23
A24: Month 19 | B24: =B23*(1-(0.05/12)) | C24: Standard Bundle (₹1,499/mo) | D24: =B24*(1499-50) | E24: =B24*'Illustrative Cost Breakdown'!B30 | F24: 0 | G24: =D24-E24 | H24: =H23+G24
A25: Month 20 | B25: =B24*(1-(0.05/12)) | C25: Standard Bundle (₹1,499/mo) | D25: =B25*(1499-50) | E25: =B25*'Illustrative Cost Breakdown'!B30 | F25: 0 | G25: =D25-E25 | H25: =H24+G25
A26: Month 21 | B26: =B25*(1-(0.05/12)) | C26: Standard Bundle (₹1,499/mo) | D26: =B26*(1499-50) | E26: =B26*'Illustrative Cost Breakdown'!B30 | F26: 0 | G26: =D26-E26 | H26: =H25+G26
A27: Month 22 | B27: =B26*(1-(0.05/12)) | C27: Standard Bundle (₹1,499/mo) | D27: =B27*(1499-50) | E27: =B27*'Illustrative Cost Breakdown'!B30 | F27: 0 | G27: =D27-E27 | H27: =H26+G27
A28: Month 23 | B28: =B27*(1-(0.05/12)) | C28: Standard Bundle (₹1,499/mo) | D28: =B28*(1499-50) | E28: =B28*'Illustrative Cost Breakdown'!B30 | F28: 0 | G28: =D28-E28 | H28: =H27+G28
A29: Month 24 | B29: =B28*(1-(0.05/12)) | C29: Standard Bundle (₹1,499/mo) | D29: =B29*(1499-50) | E29: =B29*'Illustrative Cost Breakdown'!B30 | F29: 0 | G29: =D29-E29 | H29: =H28+G29
A32: Development Cost Amortization | B32: =-'Illustrative Cost Breakdown'!D5 | G32: Total Cohort Net Profit | H32: =H29+B32

Sheet Competitor & Elasticity
A1: COMPETITOR MAPPING & CONJOINT PRICE ELASTICITY
A3: PRIMARY RESEARCH CONJOINT VALUE MODEL (N=132)
A4: Bundle Plan Option | B4: Monthly Price Point (₹) | C4: Respondent Acceptance % | D4: Monthly Revenue Yield (₹) | E4: Financial Suitability / Sweet Spot Analysis
A5: Altura Starter | B5: 499 | C5: 0.82 | D5: =B5*C5 | E5: High acceptance for entry-level; limited monetization capability
A6: Altura Connect | B6: 999 | C6: 0.68 | D6: =B6*C6 | E6: Steady standard tier; good for couples and smaller households
A7: Family Secure (Promo) | B7: 999 | C7: 0.89 | D7: =B7*C7 | E7: OPTIMAL SWEET SPOT: Lifts acceptance by 111% vs. standard price
A8: Family Secure (Standard) | B8: 1499 | C8: 0.42 | D8: =B8*C8 | E8: High long-term ARPU but requires promo introductory hook to convert
A9: Altura Infinite | B9: 2999 | C9: 0.15 | D9: =B9*C9 | E9: Niche high-value play; generates premium ARPU from 15% of market
A12: COMPETITOR CONVERGENCE OFFERING COMPARISON
A13: Convergence Metric | B13: Reliance Jio (Broadband-first) | C13: Vodafone Idea (Vi) (No Fiber) | D13: Altura Communications (Ours)
A14: Core Convergence Offer | B14: Broadband + TV + OTT bundles | C14: Partnership-only (No owned Fiber) | D14: Broadband + TV + Mobile SIMs + Bank + Security
A15: Entry Price Point | B15: ₹399/mo (standalone fiber) | C15: N/A (mobile only) | D15: ₹499/mo (Starter Bundle)
A16: Home Security integration | B16: JioFiber smart camera (unintegrated app) | C16: No home security products | D16: Altura Xsafe camera with cellular failover backup
A17: Loyalty Rewards | B17: JioPrime coupon tie-ups | C17: Vi Rewards app checkouts | D17: Altura Thanks Coins (integrated bill cashbacks)
A18: Financial Integration | B18: UPI Payments wallet | C18: Paytm/Third-party tie-ups | D18: Altura Payments Bank (7% interest & Safe Pay)
